mol2scad.py
mol2scad-1.1.0.dist-info/METADATA
mol2scad-1.1.0.dist-info/WHEEL
mol2scad-1.1.0.dist-info/entry_points.txt
mol2scad-1.1.0.dist-info/top_level.txt
mol2scad-1.1.0.dist-info/RECORD
